localizesh_processor_rst/__init__.py
localizesh_processor_rst/processor.py
localizesh_processor_rst/utils/__init__.py
localizesh_processor_rst/utils/convert_to_ast.py
localizesh_processor_rst/utils/convert_to_rst.py
localizesh_processor_rst/utils/post_parse_doctree.py
localizesh_processor_rst-0.1.7.dist-info/METADATA
localizesh_processor_rst-0.1.7.dist-info/WHEEL
localizesh_processor_rst-0.1.7.dist-info/top_level.txt
localizesh_processor_rst-0.1.7.dist-info/RECORD
